{
  "image_path": "data\\samples\\104.jpg",
  "success": true,
  "combined_text": "Dab hlsk: Sls i oi Consultant Erosicn  lal: Scc cT . Temferal Pelvadted Tn Sc lerosed Maslold intact ( Son € oufllint Naine bone Ossicle PIA Imbedante UlvIcl",
  "detailed_results": [
    {
      "text": "Dab",
      "confidence": 0.057843463965692454,
      "bbox": [
        [
          541,
          79
        ],
        [
          577,
          79
        ],
        [
          577,
          99
        ],
        [
          541,
          99
        ]
      ]
    },
    {
      "text": "hlsk:",
      "confidence": 0.3389538524896401,
      "bbox": [
        [
          569,
          65
        ],
        [
          637,
          65
        ],
        [
          637,
          109
        ],
        [
          569,
          109
        ]
      ]
    },
    {
      "text": "Sls",
      "confidence": 0.10554923947674816,
      "bbox": [
        [
          172,
          90
        ],
        [
          240,
          90
        ],
        [
          240,
          144
        ],
        [
          172,
          144
        ]
      ]
    },
    {
      "text": "i",
      "confidence": 0.2759630368837094,
      "bbox": [
        [
          287,
          97
        ],
        [
          342,
          97
        ],
        [
          342,
          136
        ],
        [
          287,
          136
        ]
      ]
    },
    {
      "text": "oi Consultant",
      "confidence": 0.23075328943422488,
      "bbox": [
        [
          70,
          130
        ],
        [
          164,
          130
        ],
        [
          164,
          156
        ],
        [
          70,
          156
        ]
      ]
    },
    {
      "text": "Erosicn  lal: Scc",
      "confidence": 0.19572882165752037,
      "bbox": [
        [
          336,
          162
        ],
        [
          504,
          162
        ],
        [
          504,
          194
        ],
        [
          336,
          194
        ]
      ]
    },
    {
      "text": "cT . Temferal",
      "confidence": 0.3548151441942243,
      "bbox": [
        [
          127,
          174
        ],
        [
          260,
          174
        ],
        [
          260,
          213
        ],
        [
          127,
          213
        ]
      ]
    },
    {
      "text": "Pelvadted",
      "confidence": 0.4030441317011594,
      "bbox": [
        [
          333,
          199
        ],
        [
          424,
          199
        ],
        [
          424,
          228
        ],
        [
          333,
          228
        ]
      ]
    },
    {
      "text": "Tn",
      "confidence": 0.9605303716844826,
      "bbox": [
        [
          431,
          199
        ],
        [
          463,
          199
        ],
        [
          463,
          219
        ],
        [
          431,
          219
        ]
      ]
    },
    {
      "text": "Sc lerosed Maslold",
      "confidence": 0.23803361055721284,
      "bbox": [
        [
          335,
          223
        ],
        [
          527,
          223
        ],
        [
          527,
          262
        ],
        [
          335,
          262
        ]
      ]
    },
    {
      "text": "intact",
      "confidence": 0.48543616859040695,
      "bbox": [
        [
          408,
          262
        ],
        [
          480,
          262
        ],
        [
          480,
          288
        ],
        [
          408,
          288
        ]
      ]
    },
    {
      "text": "( Son €",
      "confidence": 0.37918947329574093,
      "bbox": [
        [
          559,
          301
        ],
        [
          673,
          301
        ],
        [
          673,
          361
        ],
        [
          559,
          361
        ]
      ]
    },
    {
      "text": "oufllint",
      "confidence": 0.16330595356298147,
      "bbox": [
        [
          574,
          20
        ],
        [
          677,
          10
        ],
        [
          679,
          53
        ],
        [
          575,
          63
        ]
      ]
    },
    {
      "text": "Naine",
      "confidence": 0.2884692979247518,
      "bbox": [
        [
          29,
          144
        ],
        [
          70,
          141
        ],
        [
          72,
          158
        ],
        [
          30,
          160
        ]
      ]
    },
    {
      "text": "bone",
      "confidence": 0.927954375743866,
      "bbox": [
        [
          260,
          171
        ],
        [
          311,
          179
        ],
        [
          308,
          203
        ],
        [
          257,
          196
        ]
      ]
    },
    {
      "text": "Ossicle",
      "confidence": 0.6419255785086836,
      "bbox": [
        [
          336,
          269
        ],
        [
          409,
          264
        ],
        [
          410,
          291
        ],
        [
          337,
          297
        ]
      ]
    },
    {
      "text": "PIA",
      "confidence": 0.75766674514623,
      "bbox": [
        [
          13,
          302
        ],
        [
          70,
          280
        ],
        [
          83,
          315
        ],
        [
          26,
          338
        ]
      ]
    },
    {
      "text": "Imbedante",
      "confidence": 0.5002139088214234,
      "bbox": [
        [
          17,
          349
        ],
        [
          111,
          303
        ],
        [
          124,
          336
        ],
        [
          30,
          382
        ]
      ]
    },
    {
      "text": "UlvIcl",
      "confidence": 0.08417749973801301,
      "bbox": [
        [
          564,
          394
        ],
        [
          723,
          351
        ],
        [
          734,
          393
        ],
        [
          575,
          436
        ]
      ]
    }
  ],
  "total_regions": 19,
  "avg_confidence": 0.38892389280930056,
  "medical_analysis": {
    "drug_keywords": [
      "l"
    ],
    "prescription_indicators": [],
    "total_medical_terms": 1,
    "confidence": "Low",
    "is_medical": false
  },
  "structured_info": {
    "dosages": [],
    "frequencies": [],
    "durations": []
  }
}