{
  "image_path": "data\\samples\\60.jpg",
  "success": true,
  "combined_text": "HealthCare   Global Enterprises  Ltdua HCg ed 45 UdCrs RaaRan Ro Exn (0r 0662 4910506ig4 Fa +91007 Baand 550m21 Patient Name 'hnaa Corporate MRD: No: Company Name OaAV Ward Consultant Name R MAL Amphotericic & Lipo $6 Ivs: 350 *d X des* whs OR . 8 ~J An pitote 40#m2 xdaxlx Y 4 wjis ok , (~J ' Q06 m 8 Name of the Doctor : 1SAVUCorlole 6 capsu_ Signature of te Docior: Qopf '-ials X Need above medicine please help me know any way _ Riclo CONALOL€ TSAVu ' \"~-1-1 week ifyou",
  "detailed_results": [
    {
      "text": "HealthCare   Global",
      "confidence": 0.9796707266773743,
      "bbox": [
        [
          264,
          72
        ],
        [
          452,
          72
        ],
        [
          452,
          102
        ],
        [
          264,
          102
        ]
      ]
    },
    {
      "text": "Enterprises  Ltdua",
      "confidence": 0.34999664267410263,
      "bbox": [
        [
          451,
          59
        ],
        [
          629,
          59
        ],
        [
          629,
          103
        ],
        [
          451,
          103
        ]
      ]
    },
    {
      "text": "HCg",
      "confidence": 0.3167976438999176,
      "bbox": [
        [
          45,
          85
        ],
        [
          139,
          85
        ],
        [
          139,
          127
        ],
        [
          45,
          127
        ]
      ]
    },
    {
      "text": "ed",
      "confidence": 0.03330266115027219,
      "bbox": [
        [
          150,
          106
        ],
        [
          180,
          106
        ],
        [
          180,
          112
        ],
        [
          150,
          112
        ]
      ]
    },
    {
      "text": "45 UdCrs RaaRan",
      "confidence": 0.11504121489180211,
      "bbox": [
        [
          273,
          99
        ],
        [
          417,
          99
        ],
        [
          417,
          117
        ],
        [
          273,
          117
        ]
      ]
    },
    {
      "text": "Ro Exn (0r",
      "confidence": 0.085071634762937,
      "bbox": [
        [
          449,
          93
        ],
        [
          519,
          93
        ],
        [
          519,
          111
        ],
        [
          449,
          111
        ]
      ]
    },
    {
      "text": "0662",
      "confidence": 0.09524683654308319,
      "bbox": [
        [
          558,
          88
        ],
        [
          614,
          88
        ],
        [
          614,
          120
        ],
        [
          558,
          120
        ]
      ]
    },
    {
      "text": "4910506ig4",
      "confidence": 0.05047522133278603,
      "bbox": [
        [
          405,
          113
        ],
        [
          493,
          113
        ],
        [
          493,
          131
        ],
        [
          405,
          131
        ]
      ]
    },
    {
      "text": "Fa +91007",
      "confidence": 0.06326420924295847,
      "bbox": [
        [
          503,
          107
        ],
        [
          587,
          107
        ],
        [
          587,
          125
        ],
        [
          503,
          125
        ]
      ]
    },
    {
      "text": "Baand",
      "confidence": 0.09964316609092343,
      "bbox": [
        [
          281,
          121
        ],
        [
          331,
          121
        ],
        [
          331,
          137
        ],
        [
          281,
          137
        ]
      ]
    },
    {
      "text": "550m21",
      "confidence": 0.14453239874386187,
      "bbox": [
        [
          337,
          119
        ],
        [
          379,
          119
        ],
        [
          379,
          133
        ],
        [
          337,
          133
        ]
      ]
    },
    {
      "text": "Patient Name",
      "confidence": 0.7820263279584715,
      "bbox": [
        [
          47,
          173
        ],
        [
          161,
          173
        ],
        [
          161,
          193
        ],
        [
          47,
          193
        ]
      ]
    },
    {
      "text": "'hnaa",
      "confidence": 0.2678479010103226,
      "bbox": [
        [
          216,
          145
        ],
        [
          435,
          145
        ],
        [
          435,
          200
        ],
        [
          216,
          200
        ]
      ]
    },
    {
      "text": "Corporate",
      "confidence": 0.9879249656420273,
      "bbox": [
        [
          432,
          194
        ],
        [
          513,
          194
        ],
        [
          513,
          214
        ],
        [
          432,
          214
        ]
      ]
    },
    {
      "text": "MRD: No:",
      "confidence": 0.7477120816505859,
      "bbox": [
        [
          49,
          207
        ],
        [
          144,
          207
        ],
        [
          144,
          233
        ],
        [
          49,
          233
        ]
      ]
    },
    {
      "text": "Company Name",
      "confidence": 0.9449822540442667,
      "bbox": [
        [
          433,
          211
        ],
        [
          561,
          211
        ],
        [
          561,
          231
        ],
        [
          433,
          231
        ]
      ]
    },
    {
      "text": "OaAV Ward",
      "confidence": 0.10887205490041808,
      "bbox": [
        [
          281,
          237
        ],
        [
          482,
          237
        ],
        [
          482,
          268
        ],
        [
          281,
          268
        ]
      ]
    },
    {
      "text": "Consultant Name",
      "confidence": 0.9970796978814217,
      "bbox": [
        [
          51,
          262
        ],
        [
          198,
          262
        ],
        [
          198,
          290
        ],
        [
          51,
          290
        ]
      ]
    },
    {
      "text": "R",
      "confidence": 0.9918133179098731,
      "bbox": [
        [
          66,
          334
        ],
        [
          96,
          334
        ],
        [
          96,
          370
        ],
        [
          66,
          370
        ]
      ]
    },
    {
      "text": "MAL",
      "confidence": 0.645816468471521,
      "bbox": [
        [
          255,
          352
        ],
        [
          332,
          352
        ],
        [
          332,
          381
        ],
        [
          255,
          381
        ]
      ]
    },
    {
      "text": "Amphotericic &",
      "confidence": 0.20997948637049113,
      "bbox": [
        [
          360,
          330
        ],
        [
          635,
          330
        ],
        [
          635,
          372
        ],
        [
          360,
          372
        ]
      ]
    },
    {
      "text": "Lipo $6",
      "confidence": 0.2544143455483288,
      "bbox": [
        [
          137,
          354
        ],
        [
          260,
          354
        ],
        [
          260,
          395
        ],
        [
          137,
          395
        ]
      ]
    },
    {
      "text": "Ivs:",
      "confidence": 0.16830211877822876,
      "bbox": [
        [
          82,
          388
        ],
        [
          146,
          388
        ],
        [
          146,
          418
        ],
        [
          82,
          418
        ]
      ]
    },
    {
      "text": "350 *d",
      "confidence": 0.6037415814491763,
      "bbox": [
        [
          313,
          397
        ],
        [
          455,
          397
        ],
        [
          455,
          435
        ],
        [
          313,
          435
        ]
      ]
    },
    {
      "text": "X",
      "confidence": 0.8383392450077906,
      "bbox": [
        [
          466,
          392
        ],
        [
          490,
          392
        ],
        [
          490,
          418
        ],
        [
          466,
          418
        ]
      ]
    },
    {
      "text": "des*",
      "confidence": 0.3737831711769104,
      "bbox": [
        [
          499,
          379
        ],
        [
          641,
          379
        ],
        [
          641,
          421
        ],
        [
          499,
          421
        ]
      ]
    },
    {
      "text": "whs",
      "confidence": 0.3704796440537341,
      "bbox": [
        [
          490,
          433
        ],
        [
          569,
          433
        ],
        [
          569,
          464
        ],
        [
          490,
          464
        ]
      ]
    },
    {
      "text": "OR .",
      "confidence": 0.23723081709037627,
      "bbox": [
        [
          202,
          502
        ],
        [
          258,
          502
        ],
        [
          258,
          532
        ],
        [
          202,
          532
        ]
      ]
    },
    {
      "text": "8",
      "confidence": 0.26241209878561733,
      "bbox": [
        [
          478,
          564
        ],
        [
          508,
          564
        ],
        [
          508,
          590
        ],
        [
          478,
          590
        ]
      ]
    },
    {
      "text": "~J",
      "confidence": 0.3475346725161309,
      "bbox": [
        [
          98,
          610
        ],
        [
          142,
          610
        ],
        [
          142,
          636
        ],
        [
          98,
          636
        ]
      ]
    },
    {
      "text": "An",
      "confidence": 0.99964885051868,
      "bbox": [
        [
          156,
          602
        ],
        [
          228,
          602
        ],
        [
          228,
          630
        ],
        [
          156,
          630
        ]
      ]
    },
    {
      "text": "pitote",
      "confidence": 0.5837993245851331,
      "bbox": [
        [
          225,
          587
        ],
        [
          335,
          587
        ],
        [
          335,
          628
        ],
        [
          225,
          628
        ]
      ]
    },
    {
      "text": "40#m2",
      "confidence": 0.2190111311562917,
      "bbox": [
        [
          417,
          599
        ],
        [
          561,
          599
        ],
        [
          561,
          643
        ],
        [
          417,
          643
        ]
      ]
    },
    {
      "text": "xdaxlx",
      "confidence": 0.33725354046635403,
      "bbox": [
        [
          583,
          581
        ],
        [
          703,
          581
        ],
        [
          703,
          623
        ],
        [
          583,
          623
        ]
      ]
    },
    {
      "text": "Y 4",
      "confidence": 0.6108805940219535,
      "bbox": [
        [
          486,
          654
        ],
        [
          542,
          654
        ],
        [
          542,
          684
        ],
        [
          486,
          684
        ]
      ]
    },
    {
      "text": "wjis",
      "confidence": 0.11045954376459122,
      "bbox": [
        [
          550,
          652
        ],
        [
          622,
          652
        ],
        [
          622,
          676
        ],
        [
          550,
          676
        ]
      ]
    },
    {
      "text": "ok ,",
      "confidence": 0.23235492797464596,
      "bbox": [
        [
          208,
          780
        ],
        [
          270,
          780
        ],
        [
          270,
          810
        ],
        [
          208,
          810
        ]
      ]
    },
    {
      "text": "(~J '",
      "confidence": 0.2285049937066631,
      "bbox": [
        [
          197,
          854
        ],
        [
          294,
          854
        ],
        [
          294,
          886
        ],
        [
          197,
          886
        ]
      ]
    },
    {
      "text": "Q06 m",
      "confidence": 0.17331920786126725,
      "bbox": [
        [
          339,
          887
        ],
        [
          497,
          887
        ],
        [
          497,
          931
        ],
        [
          339,
          931
        ]
      ]
    },
    {
      "text": "8",
      "confidence": 0.988193164412511,
      "bbox": [
        [
          508,
          942
        ],
        [
          538,
          942
        ],
        [
          538,
          974
        ],
        [
          508,
          974
        ]
      ]
    },
    {
      "text": "Name of the Doctor :",
      "confidence": 0.6766037233728928,
      "bbox": [
        [
          85,
          978
        ],
        [
          254,
          978
        ],
        [
          254,
          1011
        ],
        [
          85,
          1011
        ]
      ]
    },
    {
      "text": "1SAVUCorlole",
      "confidence": 0.3737932533166386,
      "bbox": [
        [
          525,
          962
        ],
        [
          786,
          962
        ],
        [
          786,
          1022
        ],
        [
          525,
          1022
        ]
      ]
    },
    {
      "text": "6",
      "confidence": 0.642524304277913,
      "bbox": [
        [
          301,
          1011
        ],
        [
          325,
          1011
        ],
        [
          325,
          1031
        ],
        [
          301,
          1031
        ]
      ]
    },
    {
      "text": "capsu_",
      "confidence": 0.3621455429395481,
      "bbox": [
        [
          364,
          990
        ],
        [
          504,
          990
        ],
        [
          504,
          1042
        ],
        [
          364,
          1042
        ]
      ]
    },
    {
      "text": "Signature of te Docior:",
      "confidence": 0.5319902865948081,
      "bbox": [
        [
          82,
          1029
        ],
        [
          289,
          1029
        ],
        [
          289,
          1078
        ],
        [
          82,
          1078
        ]
      ]
    },
    {
      "text": "Qopf",
      "confidence": 0.06727291643619537,
      "bbox": [
        [
          480,
          1026
        ],
        [
          607,
          1026
        ],
        [
          607,
          1071
        ],
        [
          480,
          1071
        ]
      ]
    },
    {
      "text": "'-ials",
      "confidence": 0.14179547037356452,
      "bbox": [
        [
          611,
          993
        ],
        [
          793,
          993
        ],
        [
          793,
          1079
        ],
        [
          611,
          1079
        ]
      ]
    },
    {
      "text": "X",
      "confidence": 0.8710559334485914,
      "bbox": [
        [
          642,
          1044
        ],
        [
          666,
          1044
        ],
        [
          666,
          1070
        ],
        [
          642,
          1070
        ]
      ]
    },
    {
      "text": "Need above medicine please help me",
      "confidence": 0.7922949860155231,
      "bbox": [
        [
          64,
          1136
        ],
        [
          670,
          1136
        ],
        [
          670,
          1184
        ],
        [
          64,
          1184
        ]
      ]
    },
    {
      "text": "know any way _",
      "confidence": 0.5020002492996054,
      "bbox": [
        [
          282,
          1186
        ],
        [
          523,
          1186
        ],
        [
          523,
          1229
        ],
        [
          282,
          1229
        ]
      ]
    },
    {
      "text": "Riclo",
      "confidence": 0.1622194549318748,
      "bbox": [
        [
          332,
          584
        ],
        [
          433,
          573
        ],
        [
          436,
          600
        ],
        [
          335,
          611
        ]
      ]
    },
    {
      "text": "CONALOL€",
      "confidence": 0.1091581526223849,
      "bbox": [
        [
          413,
          835
        ],
        [
          609,
          811
        ],
        [
          613,
          842
        ],
        [
          417,
          866
        ]
      ]
    },
    {
      "text": "TSAVu",
      "confidence": 0.604953950397752,
      "bbox": [
        [
          299,
          846
        ],
        [
          422,
          835
        ],
        [
          424,
          868
        ],
        [
          301,
          879
        ]
      ]
    },
    {
      "text": "' \"~-1-1",
      "confidence": 0.20108856849530934,
      "bbox": [
        [
          509,
          875
        ],
        [
          661,
          861
        ],
        [
          662,
          907
        ],
        [
          511,
          921
        ]
      ]
    },
    {
      "text": "week",
      "confidence": 0.6582730412483215,
      "bbox": [
        [
          537,
          933
        ],
        [
          661,
          919
        ],
        [
          664,
          954
        ],
        [
          540,
          968
        ]
      ]
    },
    {
      "text": "ifyou",
      "confidence": 0.9998916692929076,
      "bbox": [
        [
          668,
          1131
        ],
        [
          764,
          1146
        ],
        [
          755,
          1190
        ],
        [
          659,
          1176
        ]
      ]
    }
  ],
  "total_regions": 56,
  "avg_confidence": 0.44024681049620773,
  "medical_analysis": {
    "drug_keywords": [
      "g",
      "l",
      "po"
    ],
    "prescription_indicators": [
      "doctor",
      "patient",
      "name",
      "signature"
    ],
    "total_medical_terms": 7,
    "confidence": "High",
    "is_medical": true
  },
  "structured_info": {
    "dosages": [],
    "frequencies": [],
    "durations": [
      [
        "1",
        "week"
      ]
    ]
  }
}