{
  "image_path": "data\\samples\\125.jpg",
  "success": true,
  "combined_text": "Mob 9899874855 DTalt Arz KD.B.5 (Delhl) Street Ballimaran, Delhi-110006 Tel : 23928493 CLINIC : 1430,Qasimjan e-mail: azizclinic@hotmail  com Dale 18 SL) Ret No 2 , Me AcJJ N- Ju + cekh Lbex Sheeba MoLuc Loz S' (21& aivex hJo ) +oi Scl-all- Ltl Ixtk : 9 Uw $r 14 Ue (sk G1 0~~ L Ca-Mi bao   2 18-8-8 Lo (8-(1-10 2m6 Dr: TIALAT AZIZ M.BIB.S Regd /No. MCi 4809 Jnalu) Bazo prsn Deils_ Delhi-6 'VACCIMTION # NERULISER #LARASIHTEEION CENTER *EAR & NOSE PIERCING Resi:N-303,TAJENCLAVE, Geelacolony, Delhi-110031 hcosda ~xh-y n Sheebe 1430",
  "detailed_results": [
    {
      "text": "Mob",
      "confidence": 0.9890952110290527,
      "bbox": [
        [
          465,
          117
        ],
        [
          501,
          117
        ],
        [
          501,
          133
        ],
        [
          465,
          133
        ]
      ]
    },
    {
      "text": "9899874855",
      "confidence": 0.9999301832075168,
      "bbox": [
        [
          503,
          109
        ],
        [
          600,
          109
        ],
        [
          600,
          134
        ],
        [
          503,
          134
        ]
      ]
    },
    {
      "text": "DTalt Arz",
      "confidence": 0.7169377171167935,
      "bbox": [
        [
          253,
          137
        ],
        [
          419,
          137
        ],
        [
          419,
          181
        ],
        [
          253,
          181
        ]
      ]
    },
    {
      "text": "KD.B.5 (Delhl)",
      "confidence": 0.38409217459314027,
      "bbox": [
        [
          327,
          179
        ],
        [
          417,
          179
        ],
        [
          417,
          195
        ],
        [
          327,
          195
        ]
      ]
    },
    {
      "text": "Street Ballimaran, Delhi-110006 Tel : 23928493",
      "confidence": 0.4557336946877397,
      "bbox": [
        [
          247,
          197
        ],
        [
          597,
          197
        ],
        [
          597,
          235
        ],
        [
          247,
          235
        ]
      ]
    },
    {
      "text": "CLINIC : 1430,Qasimjan",
      "confidence": 0.661578346001937,
      "bbox": [
        [
          83,
          217
        ],
        [
          253,
          217
        ],
        [
          253,
          237
        ],
        [
          83,
          237
        ]
      ]
    },
    {
      "text": "e-mail:",
      "confidence": 0.5931226229316235,
      "bbox": [
        [
          239,
          233
        ],
        [
          283,
          233
        ],
        [
          283,
          249
        ],
        [
          239,
          249
        ]
      ]
    },
    {
      "text": "azizclinic@hotmail ",
      "confidence": 0.7606310353136359,
      "bbox": [
        [
          279,
          224
        ],
        [
          404,
          224
        ],
        [
          404,
          252
        ],
        [
          279,
          252
        ]
      ]
    },
    {
      "text": "com",
      "confidence": 0.9997991698480148,
      "bbox": [
        [
          403,
          229
        ],
        [
          433,
          229
        ],
        [
          433,
          243
        ],
        [
          403,
          243
        ]
      ]
    },
    {
      "text": "Dale",
      "confidence": 0.9995176792144775,
      "bbox": [
        [
          461,
          257
        ],
        [
          497,
          257
        ],
        [
          497,
          273
        ],
        [
          461,
          273
        ]
      ]
    },
    {
      "text": "18",
      "confidence": 0.5829369534749648,
      "bbox": [
        [
          502,
          238
        ],
        [
          538,
          238
        ],
        [
          538,
          268
        ],
        [
          502,
          268
        ]
      ]
    },
    {
      "text": "SL)",
      "confidence": 0.2623322051598677,
      "bbox": [
        [
          550,
          236
        ],
        [
          618,
          236
        ],
        [
          618,
          268
        ],
        [
          550,
          268
        ]
      ]
    },
    {
      "text": "Ret No",
      "confidence": 0.7669606646674576,
      "bbox": [
        [
          77,
          271
        ],
        [
          127,
          271
        ],
        [
          127,
          287
        ],
        [
          77,
          287
        ]
      ]
    },
    {
      "text": "2 ,",
      "confidence": 0.7634647881152183,
      "bbox": [
        [
          420,
          292
        ],
        [
          470,
          292
        ],
        [
          470,
          316
        ],
        [
          420,
          316
        ]
      ]
    },
    {
      "text": "Me AcJJ",
      "confidence": 0.1070272610013499,
      "bbox": [
        [
          192,
          294
        ],
        [
          375,
          294
        ],
        [
          375,
          334
        ],
        [
          192,
          334
        ]
      ]
    },
    {
      "text": "N-",
      "confidence": 0.23724796380692564,
      "bbox": [
        [
          539,
          351
        ],
        [
          597,
          351
        ],
        [
          597,
          387
        ],
        [
          539,
          387
        ]
      ]
    },
    {
      "text": "Ju",
      "confidence": 0.24746200911889807,
      "bbox": [
        [
          51,
          361
        ],
        [
          163,
          361
        ],
        [
          163,
          429
        ],
        [
          51,
          429
        ]
      ]
    },
    {
      "text": "+",
      "confidence": 0.5294656554963275,
      "bbox": [
        [
          241,
          377
        ],
        [
          289,
          377
        ],
        [
          289,
          413
        ],
        [
          241,
          413
        ]
      ]
    },
    {
      "text": "cekh Lbex",
      "confidence": 0.3296441960004426,
      "bbox": [
        [
          303,
          362
        ],
        [
          527,
          362
        ],
        [
          527,
          418
        ],
        [
          303,
          418
        ]
      ]
    },
    {
      "text": "Sheeba MoLuc",
      "confidence": 0.25680739592596646,
      "bbox": [
        [
          39,
          418
        ],
        [
          340,
          418
        ],
        [
          340,
          479
        ],
        [
          39,
          479
        ]
      ]
    },
    {
      "text": "Loz",
      "confidence": 0.2673434918166203,
      "bbox": [
        [
          388,
          420
        ],
        [
          497,
          420
        ],
        [
          497,
          457
        ],
        [
          388,
          457
        ]
      ]
    },
    {
      "text": "S'",
      "confidence": 0.9071613848632137,
      "bbox": [
        [
          509,
          411
        ],
        [
          551,
          411
        ],
        [
          551,
          447
        ],
        [
          509,
          447
        ]
      ]
    },
    {
      "text": "(21&",
      "confidence": 0.15360499918460846,
      "bbox": [
        [
          568,
          456
        ],
        [
          638,
          456
        ],
        [
          638,
          482
        ],
        [
          568,
          482
        ]
      ]
    },
    {
      "text": "aivex",
      "confidence": 0.2727410520590371,
      "bbox": [
        [
          73,
          491
        ],
        [
          171,
          491
        ],
        [
          171,
          529
        ],
        [
          73,
          529
        ]
      ]
    },
    {
      "text": "hJo )",
      "confidence": 0.14478230925925803,
      "bbox": [
        [
          180,
          486
        ],
        [
          276,
          486
        ],
        [
          276,
          518
        ],
        [
          180,
          518
        ]
      ]
    },
    {
      "text": "+oi",
      "confidence": 0.15580262632693279,
      "bbox": [
        [
          415,
          467
        ],
        [
          479,
          467
        ],
        [
          479,
          527
        ],
        [
          415,
          527
        ]
      ]
    },
    {
      "text": "Scl-all-",
      "confidence": 0.5122447743861911,
      "bbox": [
        [
          71,
          540
        ],
        [
          265,
          540
        ],
        [
          265,
          581
        ],
        [
          71,
          581
        ]
      ]
    },
    {
      "text": "Ltl",
      "confidence": 0.16054559810480537,
      "bbox": [
        [
          305,
          530
        ],
        [
          400,
          530
        ],
        [
          400,
          568
        ],
        [
          305,
          568
        ]
      ]
    },
    {
      "text": "Ixtk : 9",
      "confidence": 0.24200636209278847,
      "bbox": [
        [
          445,
          503
        ],
        [
          638,
          503
        ],
        [
          638,
          584
        ],
        [
          445,
          584
        ]
      ]
    },
    {
      "text": "Uw $r 14",
      "confidence": 0.2187759600934776,
      "bbox": [
        [
          315,
          571
        ],
        [
          491,
          571
        ],
        [
          491,
          611
        ],
        [
          315,
          611
        ]
      ]
    },
    {
      "text": "Ue",
      "confidence": 0.13963179620253532,
      "bbox": [
        [
          501,
          563
        ],
        [
          584,
          563
        ],
        [
          584,
          592
        ],
        [
          501,
          592
        ]
      ]
    },
    {
      "text": "(sk",
      "confidence": 0.13163974389556124,
      "bbox": [
        [
          86,
          592
        ],
        [
          148,
          592
        ],
        [
          148,
          620
        ],
        [
          86,
          620
        ]
      ]
    },
    {
      "text": "G1",
      "confidence": 0.07526618709320536,
      "bbox": [
        [
          168,
          590
        ],
        [
          248,
          590
        ],
        [
          248,
          622
        ],
        [
          168,
          622
        ]
      ]
    },
    {
      "text": "0~~",
      "confidence": 0.24730999696400974,
      "bbox": [
        [
          89,
          651
        ],
        [
          153,
          651
        ],
        [
          153,
          669
        ],
        [
          89,
          669
        ]
      ]
    },
    {
      "text": "L",
      "confidence": 0.833074055259786,
      "bbox": [
        [
          198,
          636
        ],
        [
          258,
          636
        ],
        [
          258,
          666
        ],
        [
          198,
          666
        ]
      ]
    },
    {
      "text": "Ca-Mi bao  ",
      "confidence": 0.10866606975744197,
      "bbox": [
        [
          285,
          607
        ],
        [
          567,
          607
        ],
        [
          567,
          684
        ],
        [
          285,
          684
        ]
      ]
    },
    {
      "text": "2",
      "confidence": 0.21767949074416126,
      "bbox": [
        [
          256,
          688
        ],
        [
          280,
          688
        ],
        [
          280,
          716
        ],
        [
          256,
          716
        ]
      ]
    },
    {
      "text": "18-8-8",
      "confidence": 0.8952929871710852,
      "bbox": [
        [
          377,
          663
        ],
        [
          516,
          663
        ],
        [
          516,
          718
        ],
        [
          377,
          718
        ]
      ]
    },
    {
      "text": "Lo (8-(1-10",
      "confidence": 0.26690531267328454,
      "bbox": [
        [
          535,
          669
        ],
        [
          667,
          669
        ],
        [
          667,
          705
        ],
        [
          535,
          705
        ]
      ]
    },
    {
      "text": "2m6",
      "confidence": 0.10134149390747889,
      "bbox": [
        [
          30,
          702
        ],
        [
          118,
          702
        ],
        [
          118,
          734
        ],
        [
          30,
          734
        ]
      ]
    },
    {
      "text": "Dr: TIALAT AZIZ",
      "confidence": 0.6562290432109423,
      "bbox": [
        [
          362,
          754
        ],
        [
          605,
          754
        ],
        [
          605,
          802
        ],
        [
          362,
          802
        ]
      ]
    },
    {
      "text": "M.BIB.S",
      "confidence": 0.615037621436105,
      "bbox": [
        [
          504,
          788
        ],
        [
          594,
          788
        ],
        [
          594,
          814
        ],
        [
          504,
          814
        ]
      ]
    },
    {
      "text": "Regd /No. MCi 4809",
      "confidence": 0.20538809020910906,
      "bbox": [
        [
          369,
          798
        ],
        [
          602,
          798
        ],
        [
          602,
          840
        ],
        [
          369,
          840
        ]
      ]
    },
    {
      "text": "Jnalu)",
      "confidence": 0.31331969781869023,
      "bbox": [
        [
          83,
          811
        ],
        [
          230,
          811
        ],
        [
          230,
          889
        ],
        [
          83,
          889
        ]
      ]
    },
    {
      "text": "Bazo prsn Deils_",
      "confidence": 0.09350394702678932,
      "bbox": [
        [
          353,
          821
        ],
        [
          587,
          821
        ],
        [
          587,
          881
        ],
        [
          353,
          881
        ]
      ]
    },
    {
      "text": "Delhi-6",
      "confidence": 0.9993162765356102,
      "bbox": [
        [
          497,
          855
        ],
        [
          596,
          855
        ],
        [
          596,
          884
        ],
        [
          497,
          884
        ]
      ]
    },
    {
      "text": "'VACCIMTION # NERULISER #LARASIHTEEION CENTER *EAR & NOSE PIERCING",
      "confidence": 0.10554526152281073,
      "bbox": [
        [
          73,
          902
        ],
        [
          618,
          902
        ],
        [
          618,
          953
        ],
        [
          73,
          953
        ]
      ]
    },
    {
      "text": "Resi:N-303,TAJENCLAVE, Geelacolony, Delhi-110031",
      "confidence": 0.6204890318442173,
      "bbox": [
        [
          167,
          939
        ],
        [
          508,
          939
        ],
        [
          508,
          970
        ],
        [
          167,
          970
        ]
      ]
    },
    {
      "text": "hcosda",
      "confidence": 0.1545860225726587,
      "bbox": [
        [
          470,
          289
        ],
        [
          566,
          281
        ],
        [
          568,
          329
        ],
        [
          471,
          337
        ]
      ]
    },
    {
      "text": "~xh-y",
      "confidence": 0.12585246785953988,
      "bbox": [
        [
          461,
          469
        ],
        [
          621,
          364
        ],
        [
          655,
          435
        ],
        [
          495,
          540
        ]
      ]
    },
    {
      "text": "n",
      "confidence": 0.5282144495340759,
      "bbox": [
        [
          117,
          696
        ],
        [
          210,
          686
        ],
        [
          212,
          718
        ],
        [
          119,
          727
        ]
      ]
    },
    {
      "text": "Sheebe",
      "confidence": 0.8598541996004286,
      "bbox": [
        [
          85,
          763
        ],
        [
          207,
          744
        ],
        [
          212,
          799
        ],
        [
          90,
          818
        ]
      ]
    },
    {
      "text": "1430",
      "confidence": 0.7523584647268919,
      "bbox": [
        [
          359,
          815
        ],
        [
          423,
          825
        ],
        [
          419,
          849
        ],
        [
          355,
          840
        ]
      ]
    }
  ],
  "total_regions": 53,
  "avg_confidence": 0.44764711683895664,
  "medical_analysis": {
    "drug_keywords": [
      "g",
      "l"
    ],
    "prescription_indicators": [
      "clinic"
    ],
    "total_medical_terms": 3,
    "confidence": "Moderate",
    "is_medical": true
  },
  "structured_info": {
    "dosages": [],
    "frequencies": [],
    "durations": []
  }
}