{
  "image_path": "data\\samples\\8.jpg",
  "success": true,
  "combined_text": "Dr. Sudip Mhuseac# < Uki ~uge lv Detusn\" 32V4/22 Klclo (vacheaal 045p4 fa lenriut {ymphmg Om Kin clo 0 Poruhu ak Alonel purord (Utahvn Gbaclo (uku d in h (a dc  Cardrat evelonen< 06t don< ( Ncraly GAt Ilahon 3 Glumr tonm | SOmpra ? 60a (--o (mont (x Normatin 0-0-( r Roy &5> (vmi RF Rf ~rt ty Wul'",
  "detailed_results": [
    {
      "text": "Dr. Sudip",
      "confidence": 0.7050010383904531,
      "bbox": [
        [
          156,
          48
        ],
        [
          370,
          48
        ],
        [
          370,
          104
        ],
        [
          156,
          104
        ]
      ]
    },
    {
      "text": "Mhuseac# < Uki",
      "confidence": 0.007099990771468798,
      "bbox": [
        [
          157,
          103
        ],
        [
          507,
          103
        ],
        [
          507,
          139
        ],
        [
          157,
          139
        ]
      ]
    },
    {
      "text": "~uge lv",
      "confidence": 0.00351293983867268,
      "bbox": [
        [
          158,
          136
        ],
        [
          592,
          136
        ],
        [
          592,
          166
        ],
        [
          158,
          166
        ]
      ]
    },
    {
      "text": "Detusn\"",
      "confidence": 0.004099779506822342,
      "bbox": [
        [
          160,
          167
        ],
        [
          454,
          167
        ],
        [
          454,
          200
        ],
        [
          160,
          200
        ]
      ]
    },
    {
      "text": "32V4/22",
      "confidence": 0.6940428666638001,
      "bbox": [
        [
          1260,
          143
        ],
        [
          1454,
          143
        ],
        [
          1454,
          216
        ],
        [
          1260,
          216
        ]
      ]
    },
    {
      "text": "Klclo",
      "confidence": 0.35356611221407147,
      "bbox": [
        [
          129,
          576
        ],
        [
          257,
          576
        ],
        [
          257,
          629
        ],
        [
          129,
          629
        ]
      ]
    },
    {
      "text": "(vacheaal",
      "confidence": 0.5019493541338164,
      "bbox": [
        [
          305,
          589
        ],
        [
          479,
          589
        ],
        [
          479,
          633
        ],
        [
          305,
          633
        ]
      ]
    },
    {
      "text": "045p4 fa",
      "confidence": 0.23005126590211902,
      "bbox": [
        [
          499,
          581
        ],
        [
          678,
          581
        ],
        [
          678,
          645
        ],
        [
          499,
          645
        ]
      ]
    },
    {
      "text": "lenriut",
      "confidence": 0.32194978894434945,
      "bbox": [
        [
          175,
          718
        ],
        [
          352,
          718
        ],
        [
          352,
          785
        ],
        [
          175,
          785
        ]
      ]
    },
    {
      "text": "{ymphmg",
      "confidence": 0.27449383622044343,
      "bbox": [
        [
          381,
          732
        ],
        [
          576,
          732
        ],
        [
          576,
          792
        ],
        [
          381,
          792
        ]
      ]
    },
    {
      "text": "Om",
      "confidence": 0.5526584672267362,
      "bbox": [
        [
          999,
          731
        ],
        [
          1073,
          731
        ],
        [
          1073,
          773
        ],
        [
          999,
          773
        ]
      ]
    },
    {
      "text": "Kin",
      "confidence": 0.18784407825274685,
      "bbox": [
        [
          1006,
          796
        ],
        [
          1100,
          796
        ],
        [
          1100,
          828
        ],
        [
          1006,
          828
        ]
      ]
    },
    {
      "text": "clo",
      "confidence": 0.9128274462551133,
      "bbox": [
        [
          200,
          842
        ],
        [
          274,
          842
        ],
        [
          274,
          892
        ],
        [
          200,
          892
        ]
      ]
    },
    {
      "text": "0",
      "confidence": 0.8208185363401412,
      "bbox": [
        [
          330,
          852
        ],
        [
          358,
          852
        ],
        [
          358,
          888
        ],
        [
          330,
          888
        ]
      ]
    },
    {
      "text": "Poruhu ak",
      "confidence": 0.12250392689635306,
      "bbox": [
        [
          378,
          844
        ],
        [
          610,
          844
        ],
        [
          610,
          894
        ],
        [
          378,
          894
        ]
      ]
    },
    {
      "text": "Alonel",
      "confidence": 0.6360433525339266,
      "bbox": [
        [
          998,
          878
        ],
        [
          1125,
          878
        ],
        [
          1125,
          922
        ],
        [
          998,
          922
        ]
      ]
    },
    {
      "text": "purord",
      "confidence": 0.14982852602713634,
      "bbox": [
        [
          1193,
          875
        ],
        [
          1376,
          875
        ],
        [
          1376,
          923
        ],
        [
          1193,
          923
        ]
      ]
    },
    {
      "text": "(Utahvn",
      "confidence": 0.17158426972593885,
      "bbox": [
        [
          397,
          947
        ],
        [
          587,
          947
        ],
        [
          587,
          987
        ],
        [
          397,
          987
        ]
      ]
    },
    {
      "text": "Gbaclo",
      "confidence": 0.16161983339637023,
      "bbox": [
        [
          999,
          949
        ],
        [
          1139,
          949
        ],
        [
          1139,
          989
        ],
        [
          999,
          989
        ]
      ]
    },
    {
      "text": "(uku d",
      "confidence": 0.13710822060207406,
      "bbox": [
        [
          1197,
          943
        ],
        [
          1377,
          943
        ],
        [
          1377,
          987
        ],
        [
          1197,
          987
        ]
      ]
    },
    {
      "text": "in",
      "confidence": 0.1908715886623038,
      "bbox": [
        [
          307,
          1025
        ],
        [
          355,
          1025
        ],
        [
          355,
          1061
        ],
        [
          307,
          1061
        ]
      ]
    },
    {
      "text": "h",
      "confidence": 0.4581952633640327,
      "bbox": [
        [
          381,
          1017
        ],
        [
          441,
          1017
        ],
        [
          441,
          1059
        ],
        [
          381,
          1059
        ]
      ]
    },
    {
      "text": "(a dc ",
      "confidence": 0.4348864614110901,
      "bbox": [
        [
          484,
          1006
        ],
        [
          600,
          1006
        ],
        [
          600,
          1056
        ],
        [
          484,
          1056
        ]
      ]
    },
    {
      "text": "Cardrat",
      "confidence": 0.7337708256812363,
      "bbox": [
        [
          1012,
          1068
        ],
        [
          1153,
          1068
        ],
        [
          1153,
          1109
        ],
        [
          1012,
          1109
        ]
      ]
    },
    {
      "text": "evelonen<",
      "confidence": 0.10047757748453875,
      "bbox": [
        [
          1172,
          1069
        ],
        [
          1363,
          1069
        ],
        [
          1363,
          1109
        ],
        [
          1172,
          1109
        ]
      ]
    },
    {
      "text": "06t",
      "confidence": 0.08265240890173932,
      "bbox": [
        [
          1378,
          1076
        ],
        [
          1451,
          1076
        ],
        [
          1451,
          1109
        ],
        [
          1378,
          1109
        ]
      ]
    },
    {
      "text": "don<",
      "confidence": 0.7002503871917725,
      "bbox": [
        [
          1372,
          1108
        ],
        [
          1471,
          1108
        ],
        [
          1471,
          1149
        ],
        [
          1372,
          1149
        ]
      ]
    },
    {
      "text": "(",
      "confidence": 0.6122349366806965,
      "bbox": [
        [
          180,
          1306
        ],
        [
          260,
          1306
        ],
        [
          260,
          1408
        ],
        [
          180,
          1408
        ]
      ]
    },
    {
      "text": "Ncraly",
      "confidence": 0.2532821390325846,
      "bbox": [
        [
          482,
          1326
        ],
        [
          661,
          1326
        ],
        [
          661,
          1380
        ],
        [
          482,
          1380
        ]
      ]
    },
    {
      "text": "GAt Ilahon",
      "confidence": 0.3262576320073229,
      "bbox": [
        [
          694,
          1314
        ],
        [
          948,
          1314
        ],
        [
          948,
          1362
        ],
        [
          694,
          1362
        ]
      ]
    },
    {
      "text": "3",
      "confidence": 0.9926918052969,
      "bbox": [
        [
          332,
          1394
        ],
        [
          382,
          1394
        ],
        [
          382,
          1478
        ],
        [
          332,
          1478
        ]
      ]
    },
    {
      "text": "Glumr",
      "confidence": 0.2859021507805771,
      "bbox": [
        [
          484,
          1396
        ],
        [
          665,
          1396
        ],
        [
          665,
          1456
        ],
        [
          484,
          1456
        ]
      ]
    },
    {
      "text": "tonm |",
      "confidence": 0.1760864843650477,
      "bbox": [
        [
          704,
          1386
        ],
        [
          823,
          1386
        ],
        [
          823,
          1431
        ],
        [
          704,
          1431
        ]
      ]
    },
    {
      "text": "SOmpra ?",
      "confidence": 0.22817153657086411,
      "bbox": [
        [
          695,
          1525
        ],
        [
          857,
          1525
        ],
        [
          857,
          1569
        ],
        [
          695,
          1569
        ]
      ]
    },
    {
      "text": "60a",
      "confidence": 0.26182736291957326,
      "bbox": [
        [
          881,
          1511
        ],
        [
          961,
          1511
        ],
        [
          961,
          1556
        ],
        [
          881,
          1556
        ]
      ]
    },
    {
      "text": "(--o",
      "confidence": 0.1902451068162918,
      "bbox": [
        [
          999,
          1507
        ],
        [
          1092,
          1507
        ],
        [
          1092,
          1540
        ],
        [
          999,
          1540
        ]
      ]
    },
    {
      "text": "(mont",
      "confidence": 0.4379078503436847,
      "bbox": [
        [
          1336,
          1508
        ],
        [
          1455,
          1508
        ],
        [
          1455,
          1551
        ],
        [
          1336,
          1551
        ]
      ]
    },
    {
      "text": "(x",
      "confidence": 0.4916903331119221,
      "bbox": [
        [
          330,
          1532
        ],
        [
          386,
          1532
        ],
        [
          386,
          1592
        ],
        [
          330,
          1592
        ]
      ]
    },
    {
      "text": "Normatin",
      "confidence": 0.46103156867780204,
      "bbox": [
        [
          674,
          1595
        ],
        [
          873,
          1595
        ],
        [
          873,
          1643
        ],
        [
          674,
          1643
        ]
      ]
    },
    {
      "text": "0-0-(",
      "confidence": 0.9437464082815886,
      "bbox": [
        [
          1006,
          1584
        ],
        [
          1109,
          1584
        ],
        [
          1109,
          1623
        ],
        [
          1006,
          1623
        ]
      ]
    },
    {
      "text": "r",
      "confidence": 0.5611516578471907,
      "bbox": [
        [
          1408,
          1732
        ],
        [
          1448,
          1732
        ],
        [
          1448,
          1764
        ],
        [
          1408,
          1764
        ]
      ]
    },
    {
      "text": "Roy",
      "confidence": 0.9949625053768824,
      "bbox": [
        [
          374,
          41
        ],
        [
          472,
          59
        ],
        [
          462,
          108
        ],
        [
          363,
          90
        ]
      ]
    },
    {
      "text": "&5>",
      "confidence": 0.0010955304774305213,
      "bbox": [
        [
          591,
          133
        ],
        [
          679,
          145
        ],
        [
          674,
          175
        ],
        [
          586,
          163
        ]
      ]
    },
    {
      "text": "(vmi",
      "confidence": 0.3295610547065735,
      "bbox": [
        [
          242,
          938
        ],
        [
          374,
          957
        ],
        [
          365,
          1001
        ],
        [
          234,
          982
        ]
      ]
    },
    {
      "text": "RF",
      "confidence": 0.4280280313059102,
      "bbox": [
        [
          1114,
          1496
        ],
        [
          1175,
          1488
        ],
        [
          1179,
          1527
        ],
        [
          1117,
          1534
        ]
      ]
    },
    {
      "text": "Rf",
      "confidence": 0.1490048659387134,
      "bbox": [
        [
          1140,
          1576
        ],
        [
          1199,
          1564
        ],
        [
          1206,
          1601
        ],
        [
          1147,
          1614
        ]
      ]
    },
    {
      "text": "~rt",
      "confidence": 0.4358130991458893,
      "bbox": [
        [
          876,
          1596
        ],
        [
          961,
          1587
        ],
        [
          963,
          1621
        ],
        [
          879,
          1631
        ]
      ]
    },
    {
      "text": "ty Wul'",
      "confidence": 0.051935959575184036,
      "bbox": [
        [
          1239,
          1794
        ],
        [
          1405,
          1730
        ],
        [
          1416,
          1773
        ],
        [
          1250,
          1836
        ]
      ]
    }
  ],
  "total_regions": 48,
  "avg_confidence": 0.38046533670412286,
  "medical_analysis": {
    "drug_keywords": [
      "mg",
      "iu",
      "g",
      "l",
      "po"
    ],
    "prescription_indicators": [
      "dr."
    ],
    "total_medical_terms": 6,
    "confidence": "High",
    "is_medical": true
  },
  "structured_info": {
    "dosages": [],
    "frequencies": [],
    "durations": []
  }
}